beekeepy/__init__.py
beekeepy/_apis/__init__.py
beekeepy/_apis/abc/__init__.py
beekeepy/_apis/abc/api.py
beekeepy/_apis/abc/api_collection.py
beekeepy/_apis/abc/rest_api_definition_helpers.py
beekeepy/_apis/abc/sendable.py
beekeepy/_apis/abc/session_holder.py
beekeepy/_apis/app_status_api/__init__.py
beekeepy/_apis/app_status_api/api_collection.py
beekeepy/_apis/app_status_api/async_api.py
beekeepy/_apis/app_status_api/sync_api.py
beekeepy/_apis/apply_session_token.py
beekeepy/_apis/beekeeper_api/__init__.py
beekeepy/_apis/beekeeper_api/api_collection.py
beekeepy/_apis/beekeeper_api/async_api.py
beekeepy/_apis/beekeeper_api/beekeeper_api_commons.py
beekeepy/_apis/beekeeper_api/sync_api.py
beekeepy/_communication/__init__.py
beekeepy/_communication/abc/__init__.py
beekeepy/_communication/abc/communicator.py
beekeepy/_communication/abc/communicator_models.py
beekeepy/_communication/abc/overseer.py
beekeepy/_communication/abc/rules.py
beekeepy/_communication/aiohttp_communicator.py
beekeepy/_communication/communicator_getter.py
beekeepy/_communication/is_url_reachable.py
beekeepy/_communication/overseers.py
beekeepy/_communication/request_communicator.py
beekeepy/_communication/rules.py
beekeepy/_communication/settings.py
beekeepy/_communication/url.py
beekeepy/_exceptions/__init__.py
beekeepy/_exceptions/base.py
beekeepy/_exceptions/common.py
beekeepy/_exceptions/detectable.py
beekeepy/_exceptions/executable.py
beekeepy/_exceptions/overseer.py
beekeepy/_executable/__init__.py
beekeepy/_executable/abc/__init__.py
beekeepy/_executable/abc/arguments.py
beekeepy/_executable/abc/config.py
beekeepy/_executable/abc/executable.py
beekeepy/_executable/abc/streams.py
beekeepy/_executable/beekeeper
beekeepy/_executable/beekeeper_arguments.py
beekeepy/_executable/beekeeper_config.py
beekeepy/_executable/beekeeper_executable.py
beekeepy/_executable/beekeeper_executable_discovery.py
beekeepy/_executable/defaults.py
beekeepy/_interface/__init__.py
hiveio_beekeepy-1.28.2.dist-info/METADATA
hiveio_beekeepy-1.28.2.dist-info/WHEEL
hiveio_beekeepy-1.28.2.dist-info/RECORD
