Metadata-Version: 2.4
Name: hiveio-beekeepy
Version: 1.28.2
Summary: All in one package for beekeeper interaction via Python interface.
Author: Mateusz Żebrak
Author-email: mzebrak@syncad.com
Requires-Python: >=3.12,<4.0
Classifier: Programming Language :: Python :: 3
Classifier: Programming Language :: Python :: 3.12
Classifier: Programming Language :: Python :: 3.13
Classifier: Programming Language :: Python :: 3.14
Requires-Dist: aiohttp (==3.11.15)
Requires-Dist: hiveio-schemas (==1.28.0)
Requires-Dist: loguru (==0.7.2)
Requires-Dist: psutil (==7.0.0)
Requires-Dist: python-dateutil (==2.8.2)
Requires-Dist: requests (==2.32.3)
Project-URL: Repository, https://gitlab.syncad.com/hive/helpy
